multimcts/__init__.py
multimcts/gamestate.pxd
multimcts/mcts.cpython-39-darwin.so
multimcts/mcts.py
multimcts/mcts.pyx
multimcts-0.6.4.dist-info/LICENSE
multimcts-0.6.4.dist-info/METADATA
multimcts-0.6.4.dist-info/WHEEL
multimcts-0.6.4.dist-info/top_level.txt
multimcts-0.6.4.dist-info/RECORD
