Metadata-Version: 2.1
Name: multimcts
Version: 0.6.4
Summary: Monte Carlo Tree Search for multiple teams
Home-page: https://github.com/taylorvance/multimcts
Author: Taylor Vance
Author-email: mirrors.cities0w@icloud.com
License: MIT
Platform: UNKNOWN
License-File: LICENSE
